clv/__init__.py
clv/configs.py
clv/dashboard.py
clv/data_access.py
clv/docs/configs.yaml
clv/docs/test_parameters.yaml
clv/executor.py
clv/functions.py
clv/main.py
clv/newcomers.py
clv/next_purchase_model.py
clv/next_purchase_prediction.py
clv/purchase_amount_model.py
clv/untitled_project/trial_d8f88c83ada676165dabae9861c34ada/checkpoints/epoch_0/checkpoint
clv/utils.py
clv_prediction-0.1.9.dist-info/LICENSE
clv_prediction-0.1.9.dist-info/METADATA
clv_prediction-0.1.9.dist-info/WHEEL
clv_prediction-0.1.9.dist-info/RECORD
