Metadata-Version: 2.3
Name: clv-prediction
Version: 0.1.9
Summary: 
Author: caglanakpinar
Author-email: cakpinar23@gmail.com
Requires-Python: >=3.11,<4.0
Classifier: Programming Language :: Python :: 3
Classifier: Programming Language :: Python :: 3.11
Classifier: Programming Language :: Python :: 3.12
Classifier: Programming Language :: Python :: 3.13
Requires-Dist: dash (>=2.18.2,<3.0.0)
Requires-Dist: google (>=3.0.0,<4.0.0)
Requires-Dist: keras-tuner (>=1.4.7,<2.0.0)
Requires-Dist: mkdocs-material (>=9.6.7,<10.0.0)
Requires-Dist: mkdocs-material-extensions (>=1.3.1,<2.0.0)
Requires-Dist: pandas (>=2.2.3,<3.0.0)
Requires-Dist: plotly (>=6.0.0,<7.0.0)
Requires-Dist: psycopg2-binary (>=2.9.10,<3.0.0)
Requires-Dist: pyarrow (>=19.0.1,<20.0.0)
Requires-Dist: pyyaml (>=6.0.2,<7.0.0)
Requires-Dist: schedule (>=1.2.2,<2.0.0)
Requires-Dist: scipy (>=1.15.2,<2.0.0)
Requires-Dist: statsmodels (>=0.14.4,<0.15.0)
Requires-Dist: tensorflow (>=2.18.0,<3.0.0)
